moxa/__init__.py
moxa/moxa.py
moxa-0.5.6.dist-info/LICENSE
moxa-0.5.6.dist-info/METADATA
moxa-0.5.6.dist-info/WHEEL
moxa-0.5.6.dist-info/top_level.txt
moxa-0.5.6.dist-info/RECORD
