Metadata-Version: 2.1
Name: moxa
Version: 0.5.6
Summary: Moxa interface
Home-page: https://gitlab.com/vascowhite/moxa
Author: Paul White
Author-email: moxa@vascowhite.co.uk
License: MIT
Platform: UNKNOWN
License-File: LICENSE
